flask_live_twcss/__init__.py
flask_live_twcss/__main__.py
flask_live_twcss/cli.py
flask_live_twcss/main.py
flask_live_twcss/static/dev.py
flask_live_twcss/static/layout.html
flask_live_twcss/static/live_reload.js
flask_live_twcss/static/tailwind.config.js
flask_live_twcss/util.py
flask_live_twcss-0.1.2.dist-info/entry_points.txt
flask_live_twcss-0.1.2.dist-info/LICENSE
flask_live_twcss-0.1.2.dist-info/METADATA
flask_live_twcss-0.1.2.dist-info/WHEEL
flask_live_twcss-0.1.2.dist-info/RECORD
