Metadata-Version: 2.1
Name: flask-live-twcss
Version: 0.1.2
Summary: A simple package that enables live tailwindcss reloading for a template based app in flask
Home-page: https://github.com/J-Josu/flask-live-twcss
License: MIT
Keywords: flask,tailwindcss,live-reload,css
Author: J-Josu
Author-email: josue.sa.trabajos@gmail.com
Requires-Python: >=3.8.10,<4.0.0
Classifier: License :: OSI Approved :: MIT License
Classifier: Programming Language :: Python :: 3
Classifier: Programming Language :: Python :: 3.9
Classifier: Programming Language :: Python :: 3.10
Classifier: Programming Language :: Python :: 3.11
Project-URL: Repository, https://github.com/J-Josu/flask-live-twcss
